TKinterManagedFrame/ManagedFrame.py
Tkinter_Managed_Frame-1.0.3.dist-info/LICENSE.txt
Tkinter_Managed_Frame-1.0.3.dist-info/METADATA
Tkinter_Managed_Frame-1.0.3.dist-info/WHEEL
Tkinter_Managed_Frame-1.0.3.dist-info/top_level.txt
Tkinter_Managed_Frame-1.0.3.dist-info/RECORD
